anthropic_tools/__init__.py
anthropic_tools/conversation.py
anthropic_tools/exceptions.py
anthropic_tools/json_type.py
anthropic_tools/parsers/__init__.py
anthropic_tools/parsers/atomic_type_parser.py
anthropic_tools/parsers/bool_parser.py
anthropic_tools/parsers/dataclass_parser.py
anthropic_tools/parsers/default.py
anthropic_tools/parsers/dict_parser.py
anthropic_tools/parsers/enum_parser.py
anthropic_tools/parsers/float_parser.py
anthropic_tools/parsers/int_parser.py
anthropic_tools/parsers/list_parser.py
anthropic_tools/parsers/none_parser.py
anthropic_tools/parsers/parser.py
anthropic_tools/parsers/str_parser.py
anthropic_tools/parsers/union_parser.py
anthropic_tools/py.typed
anthropic_tools/tools/__init__.py
anthropic_tools/tools/basic_set.py
anthropic_tools/tools/sets.py
anthropic_tools/tools/tools.py
anthropic_tools/tools/union.py
anthropic_tools/tools/wrapper.py
anthropic_tools-1.0.5.dist-info/LICENSE
anthropic_tools-1.0.5.dist-info/METADATA
anthropic_tools-1.0.5.dist-info/WHEEL
anthropic_tools-1.0.5.dist-info/RECORD
