Metadata-Version: 2.1
Name: anthropic-tools
Version: 1.0.5
Summary: Simplifies the usage of Anthropic Claude's tool use by generating the schemas and parsing the responses for you.
Home-page: https://github.com/rizerphe/anthropic-tools
License: MIT
Keywords: nlp,anthropic,claude,claude3,claude-api,wrapper,functions,typing,docstring,docstrings,decorators,signatures,parsing
Author: rizerphe
Author-email: 44440399+rizerphe@users.noreply.github.com
Requires-Python: >=3.8,<4.0
Classifier: License :: OSI Approved :: MIT License
Classifier: Programming Language :: Python :: 3
Classifier: Programming Language :: Python :: 3.8
Classifier: Programming Language :: Python :: 3.9
Classifier: Programming Language :: Python :: 3.10
Classifier: Programming Language :: Python :: 3.11
Requires-Dist: anthropic (>=0.25.6,<0.26.0)
Requires-Dist: docstring-parser (>=0.15,<0.16)
Requires-Dist: typing-extensions (>=4.6.3,<5.0.0)
Project-URL: Documentation, https://anthropic-tools.readthedocs.io/
